[
  {
    "date": "01",
    "day": "Friday"
  },
  {
    "date": "02",
    "day": "Saturday"
  },
  {
    "date": "03",
    "day": "Sunday"
  },
  {
    "date": "04",
    "day": "Monday"
  },
  {
    "date": "05",
    "day": "Tuesday"
  },
  {
    "date": "06",
    "day": "Wednesday"
  },
  {
    "date": "07",
    "day": "Thursday"
  },
  {
    "date": "08",
    "day": "Friday"
  },
  {
    "date": "09",
    "day": "Saturday"
  },
  {
    "date": "10",
    "day": "Sunday"
  },
  {
    "date": "11",
    "day": "Monday"
  },
  {
    "date": "12",
    "day": "Tuesday"
  },
  {
    "date": "13",
    "day": "Wednesday"
  },
  {
    "date": "14",
    "day": "Thursday"
  },
  {
    "date": "15",
    "day": "Friday"
  },
  {
    "date": "16",
    "day": "Saturday"
  },
  {
    "date": "17",
    "day": "Sunday"
  },
  {
    "date": "18",
    "day": "Monday"
  },
  {
    "date": "19",
    "day": "Tuesday"
  },
  {
    "date": "20",
    "day": "Wednesday"
  },
  {
    "date": "21",
    "day": "Thursday"
  },
  {
    "date": "22",
    "day": "Friday"
  },
  {
    "date": "23",
    "day": "Saturday"
  },
  {
    "date": "24",
    "day": "Sunday"
  },
  {
    "date": "25",
    "day": "Monday"
  },
  {
    "date": "26",
    "day": "Tuesday"
  },
  {
    "date": "27",
    "day": "Wednesday"
  },
  {
    "date": "28",
    "day": "Thursday"
  },
  {
    "date": "29",
    "day": "Friday"
  },
  {
    "date": "30",
    "day": "Saturday"
  },
  {
    "date": "31",
    "day": "Sunday"
  }
]